odoo/addons/mrp_subcontracting_purchase_link/README.rst
odoo/addons/mrp_subcontracting_purchase_link/__init__.py
odoo/addons/mrp_subcontracting_purchase_link/__manifest__.py
odoo/addons/mrp_subcontracting_purchase_link/hooks.py
odoo/addons/mrp_subcontracting_purchase_link/i18n/es.po
odoo/addons/mrp_subcontracting_purchase_link/i18n/fr.po
odoo/addons/mrp_subcontracting_purchase_link/i18n/hr.po
odoo/addons/mrp_subcontracting_purchase_link/i18n/it.po
odoo/addons/mrp_subcontracting_purchase_link/i18n/ja.po
odoo/addons/mrp_subcontracting_purchase_link/i18n/mrp_subcontracting_purchase_link.pot
odoo/addons/mrp_subcontracting_purchase_link/i18n/pt_BR.po
odoo/addons/mrp_subcontracting_purchase_link/models/__init__.py
odoo/addons/mrp_subcontracting_purchase_link/models/mrp_production.py
odoo/addons/mrp_subcontracting_purchase_link/models/purchase_order.py
odoo/addons/mrp_subcontracting_purchase_link/models/stock_picking.py
odoo/addons/mrp_subcontracting_purchase_link/readme/CONTRIBUTORS.md
odoo/addons/mrp_subcontracting_purchase_link/readme/DESCRIPTION.md
odoo/addons/mrp_subcontracting_purchase_link/static/description/icon.png
odoo/addons/mrp_subcontracting_purchase_link/static/description/index.html
odoo/addons/mrp_subcontracting_purchase_link/tests/__init__.py
odoo/addons/mrp_subcontracting_purchase_link/tests/test_mrp_subcontracting_purchase_link.py
odoo/addons/mrp_subcontracting_purchase_link/views/mrp_production_views.xml
odoo/addons/mrp_subcontracting_purchase_link/views/purchase_order_views.xml
odoo_addon_mrp_subcontracting_purchase_link-19.0.1.0.0.2.dist-info/METADATA
odoo_addon_mrp_subcontracting_purchase_link-19.0.1.0.0.2.dist-info/WHEEL
odoo_addon_mrp_subcontracting_purchase_link-19.0.1.0.0.2.dist-info/top_level.txt
odoo_addon_mrp_subcontracting_purchase_link-19.0.1.0.0.2.dist-info/RECORD
