Metadata-Version: 2.1
Name: odoo-addon-mrp_subcontracting_purchase_link
Version: 19.0.1.0.0.2
Requires-Dist: odoo==19.0.*
Summary: Link Purchase Order Line to Subcontract Productions
Home-page: https://github.com/OCA/manufacture
License: LGPL-3
Author: Quartile Limited, ForgeFlow, Odoo Community Association (OCA)
Author-email: support@odoo-community.org
Classifier: Programming Language :: Python
Classifier: Framework :: Odoo
Classifier: Framework :: Odoo :: 19.0
Classifier: License :: OSI Approved :: GNU Lesser General Public License v3 (LGPLv3)
